Metadata-Version: 2.1
Name: EurekaAPI
Version: 0.0.6
Home-page: https://github.com/Eureka-API/EurekaPy
Download-URL: https://github.com/Eureka-API/EurekaPy
Author: Cipher58
Author-email: info@timewiserobot.com
License: Lily 1.0
Classifier: Programming Language :: Python :: 3
Classifier: Operating System :: OS Independent
License-File: LICENSE
Requires-Dist: Janex
